{"A": {"columns": 3, "desc": ["000", "0x0", "x0x", "x0x", "xxx", "x0x", "000"]}, 
"B": {"columns": 3, "desc": ["000", "xx0", "x0x", "xx0", "x0x", "xxx", "000"]},
"C": {"columns": 3, "desc": ["000", "0x0", "x0x", "x00", "x0x", "0x0", "000"]},
"D": {"columns": 3, "desc": ["000", "xx0", "x0x", "x0x", "x0x", "xx0", "000"]},
"E": {"columns": 3, "desc": ["000", "xxx", "x00", "xxx", "x00", "xxx", "000"]},
"F": {"columns": 3, "desc": ["000", "xxx", "x00", "xxx", "x00", "x00", "000"]},
"G": {"columns": 4, "desc": ["0000", "0xx0", "x000", "x0xx", "x00x", "0xx0", "0000"]},
"H": {"columns": 3, "desc": ["000", "x0x", "x0x", "xxx", "x0x", "x0x", "000"]},
"I": {"columns": 3, "desc": ["000", "xxx", "0x0", "0x0", "0x0", "xxx", "000"]},
"J": {"columns": 3, "desc": ["000", "xxx", "00x", "00x", "x0x", "0x0", "000"]},
"K": {"columns": 3, "desc": ["000", "x0x", "x0x", "xx0", "x0x", "x0x", "000"]},
"L": {"columns": 3, "desc": ["000", "x00", "x00", "x00", "x00", "xxx", "000"]},
"M": {"columns": 5, "desc": ["00000", "x000x", "xx0xx", "x0x0x", "x000x", "x000x", "00000"]},
"N": {"columns": 4, "desc": ["0000", "x00x", "x00x", "xx0x", "x0xx", "x00x", "0000"]},
"O": {"columns": 3, "desc": ["000", "0x0", "x0x", "x0x", "x0x", "0x0", "000"]},
"P": {"columns": 3, "desc": ["000", "xx0", "x0x", "x0x", "xx0", "x00", "000"]},
"Q": {"columns": 3, "desc": ["000", "0x0", "x0x", "x0x", "x0x", "0x0", "00x"]},
"R": {"columns": 3, "desc": ["000", "xx0", "x0x", "x0x", "xx0", "x0x", "000"]},
"S": {"columns": 3, "desc": ["000", "0xx", "x00", "0x0", "00x", "xx0", "000"]},
"T": {"columns": 3, "desc": ["000", "xxx", "0x0", "0x0", "0x0", "0x0", "000"]},
"U": {"columns": 4, "desc": ["0000", "x00x", "x00x", "x00x", "x00x", "0xx0", "0000"]},
"V": {"columns": 3, "desc": ["000", "x0x", "x0x", "x0x", "x0x", "0x0", "000"]},
"W": {"columns": 5, "desc": ["00000", "x000x", "x000x", "x000x", "x0x0x", "0x0x0", "00000"]},
"X": {"columns": 3, "desc": ["000", "x0x", "x0x", "0x0", "x0x", "x0x", "000"]},
"Y": {"columns": 3, "desc": ["000", "x0x", "x0x", "0x0", "0x0", "0x0", "000"]},
"Z": {"columns": 3, "desc": ["000", "xxx", "00x", "0x0", "x00", "xxx", "000"]},
",": {"columns": 2, "desc": ["00", "00", "00", "00", "00", "x0", "x0"]},
".": {"columns": 2, "desc": ["00", "00", "00", "00", "00", "x0", "00"]},
"'": {"columns": 2, "desc": ["00", "x0", "x0", "00", "00", "00", "00"]},
"!": {"columns": 2, "desc": ["00", "x0", "x0", "x0", "00", "x0", "00"]},
"?": {"columns": 3, "desc": ["000", "xx0", "00x", "0x0", "000", "0x0", "000"]},
" ": {"columns": 1, "desc": ["0", "0", "0", "0", "0", "0", "0"]},
"1": {"columns": 2, "desc": ["00", "0x", "xx", "0x", "0x", "0x", "00"]},
"2": {"columns": 3, "desc": ["000", "xxx", "00x", "xxx", "x00", "xxx", "000"]},
"3": {"columns": 3, "desc": ["000", "xxx", "00x", "xxx", "00x", "xxx", "000"]},
"4": {"columns": 3, "desc": ["000", "x0x", "x0x", "xxx", "00x", "00x", "000"]},
"5": {"columns": 3, "desc": ["000", "xxx", "x00", "xxx", "00x", "xxx", "000"]},
"6": {"columns": 3, "desc": ["000", "xxx", "x00", "xxx", "x0x", "xxx", "000"]},
"7": {"columns": 3, "desc": ["000", "xxx", "00x", "00x", "00x", "00x", "000"]},
"8": {"columns": 3, "desc": ["000", "xxx", "x0x", "xxx", "x0x", "xxx", "000"]},
"9": {"columns": 3, "desc": ["000", "xxx", "x0x", "xxx", "00x", "xxx", "000"]},
"0": {"columns": 3, "desc": ["000", "xxx", "x0x", "x0x", "x0x", "xxx", "000"]}
}
